ansys/fluent/interface/__init__.py
ansys/fluent/interface/post_objects/__init__.py
ansys/fluent/interface/post_objects/check_in_notebook.py
ansys/fluent/interface/post_objects/meta.py
ansys/fluent/interface/post_objects/post_helper.py
ansys/fluent/interface/post_objects/post_object_definitions.py
ansys/fluent/interface/post_objects/post_objects_container.py
ansys/fluent/interface/post_objects/singleton_meta.py
ansys/fluent/visualization/__init__.py
ansys/fluent/visualization/base/__init__.py
ansys/fluent/visualization/base/renderer.py
ansys/fluent/visualization/config.py
ansys/fluent/visualization/containers.py
ansys/fluent/visualization/contour.py
ansys/fluent/visualization/graphics/__init__.py
ansys/fluent/visualization/graphics/graphics_objects.py
ansys/fluent/visualization/graphics/graphics_windows.py
ansys/fluent/visualization/graphics/graphics_windows_manager.py
ansys/fluent/visualization/graphics/pyvista/__init__.py
ansys/fluent/visualization/graphics/pyvista/renderer.py
ansys/fluent/visualization/graphics/single_qt_windows.py
ansys/fluent/visualization/matplotlib/__init__.py
ansys/fluent/visualization/plotter/__init__.py
ansys/fluent/visualization/plotter/matplotlib/__init__.py
ansys/fluent/visualization/plotter/matplotlib/renderer.py
ansys/fluent/visualization/plotter/plotter_objects.py
ansys/fluent/visualization/plotter/plotter_windows.py
ansys/fluent/visualization/plotter/plotter_windows_manager.py
ansys/fluent/visualization/plotter/pyvista/__init__.py
ansys/fluent/visualization/plotter/pyvista/renderer.py
ansys/fluent/visualization/post_data_extractor.py
ansys/fluent/visualization/pyvista/__init__.py
ansys/fluent/visualization/registrar.py
ansys/fluent/visualization/renderer.py
ansys/fluent/visualization/visualization_windows_manager.py
ansys_fluent_visualization-0.22.1.dist-info/METADATA
ansys_fluent_visualization-0.22.1.dist-info/WHEEL
ansys_fluent_visualization-0.22.1.dist-info/licenses/AUTHORS
ansys_fluent_visualization-0.22.1.dist-info/licenses/LICENSE
ansys_fluent_visualization-0.22.1.dist-info/RECORD
