Metadata-Version: 2.4
Name: ansys-fluent-visualization
Version: 0.22.1
Summary: A python wrapper for ansys Fluent visualization
License: MIT
License-File: AUTHORS
License-File: LICENSE
Author: ANSYS, Inc.
Author-email: ansys.support@ansys.com
Maintainer: PyAnsys developers
Maintainer-email: pyansys.maintainers@ansys.com
Requires-Python: >=3.10,<3.14
Classifier: Development Status :: 4 - Beta
Classifier: License :: OSI Approved :: MIT License
Classifier: Operating System :: OS Independent
Classifier: Programming Language :: Python :: 3
Classifier: Programming Language :: Python :: 3.10
Classifier: Programming Language :: Python :: 3.11
Classifier: Programming Language :: Python :: 3.12
Classifier: Programming Language :: Python :: 3.13
Provides-Extra: interactive
Provides-Extra: single-window
Requires-Dist: ansys-fluent-core (>=0.35.0,<0.36.0)
Requires-Dist: importlib-metadata (>=4.0,<5.0) ; python_version < "3.9"
Requires-Dist: matplotlib (>=3.6.0)
Requires-Dist: pyside6 (>=6.8.1,<6.9.0) ; extra == "single-window"
Requires-Dist: pyvista (>=0.44.0)
Requires-Dist: pyvistaqt (>=0.11.1,<0.12.0) ; extra == "interactive" or extra == "single-window"
Project-URL: Documentation, https://visualization.fluent.docs.pyansys.com/
Project-URL: Repository, https://github.com/ansys/pyfluent-visualization
Project-URL: Source, https://github.com/ansys/pyfluent-visualization
Project-URL: Tracker, https://github.com/ansys/pyfluent-visualization/issues
